migraine_model/__init__.py
migraine_model/cli.py
migraine_model/data_handler.py
migraine_model/migraine_predictor.py
migraine_model/migraine_predictor_extension.py
migraine_model/model.py
migraine_model/new_data_migraine_predictor.py
pipeline/__init__.py
pipeline/data_ingestion.py
migraine_prediction-0.1.3.dist-info/METADATA
migraine_prediction-0.1.3.dist-info/WHEEL
migraine_prediction-0.1.3.dist-info/entry_points.txt
migraine_prediction-0.1.3.dist-info/top_level.txt
migraine_prediction-0.1.3.dist-info/RECORD
